pytmb/Planner.py
pytmb/Transit.py
pytmb/__init__.py
pytmb/enums.py
pytmb/iBus.py
pytmb/iMetro.py
pytmb/models/PlannerModel.py
pytmb/models/TransitModels/__init__.py
pytmb/models/TransitModels/geo.py
pytmb/models/TransitModels/lines.py
pytmb/models/TransitModels/routes.py
pytmb/models/iBusModel.py
pytmb/models/iMetroModel.py
pytmb/py.typed
pytmb-0.1.1b1.dist-info/licenses/LICENSE
pytmb-0.1.1b1.dist-info/WHEEL
pytmb-0.1.1b1.dist-info/METADATA
pytmb-0.1.1b1.dist-info/RECORD
