Metadata-Version: 2.4
Name: pytmb
Version: 0.1.1b1
Summary: An unofficial python client for Barcelona public transport (TMB) API.
Author: Goktug Alperen Kurt
Author-email: Goktug Alperen Kurt <244225901+apikurt@users.noreply.github.com>
License-Expression: MIT
License-File: LICENSE
Classifier: Programming Language :: Python :: 3
Classifier: Operating System :: OS Independent
Classifier: Development Status :: 4 - Beta
Classifier: Intended Audience :: Developers
Classifier: License :: OSI Approved :: MIT License
Classifier: Topic :: Software Development :: Libraries :: Python Modules
Classifier: Topic :: Utilities
Requires-Dist: pydantic>=2.12.4
Requires-Dist: requests>=2.32.5
Requires-Python: >=3.10
Project-URL: Homepage, https://github.com/apikurt/pytmb
Project-URL: Issues, https://github.com/apikurt/pytmb/issues
Project-URL: Repository, https://github.com/apikurt/pytmb
